[
    {"id" : "1" , "title" : "Pashmina Jersey", "price" : "30K", "imgs" : ["/2.png", "/L@.png", "/2.png"], "desc" : "Jilbab Pashmina", "Kategori" : "Palestina"},
    {"id" : "2" , "title" : "Pashmina Palestina", "price" : "30K", "imgs" : ["/2.png", "/2.png", "/2.png"], "desc" : "Jilbab Pashmina", "Kategori" : "Palestina"},
    {"id" : "3" , "title" : "Persegi Corak", "price" : "30K", "imgs" : ["/2.png", "/2.png", "/2.png"], "desc" : "Jilbab Pashmina", "Kategori" : "Palestina"},
    {"id" : "4" , "title" : "Persegi Polos", "price" : "30K", "imgs" : ["/2.png", "/2.png", "/2.png"], "desc" : "Jilbab Pashmina", "Kategori" : "Palestina"},
    {"id" : "5" , "title" : "Pashmina Jersey", "price" : "30K", "imgs" : ["/2.png", "/2.png", "/2.png"], "desc" : "Jilbab Pashmina", "Kategori" : "Palestina"},
    {"id" : "6" , "title" : "Pashmina Jersey", "price" : "30K", "imgs" : ["/2.png", "/2.png", "/2.png"], "desc" : "Jilbab Pashmina", "Kategori" : "Palestina"},
    {"id" : "7" , "title" : "Pashmina Jersey", "price" : "30K", "imgs" : ["/2.png", "/2.png", "/2.png"], "desc" : "Jilbab Pashmina", "Kategori" : "Palestina"},
    {"id" : "8" , "title" : "Pashmina Jersey", "price" : "30K", "imgs" : ["/2.png", "/2.png", "/2.png"], "desc" : "Jilbab Pashmina", "Kategori" : "Palestina"},
    {"id" : "9" , "title" : "Pashmina Jersey", "price" : "30K", "imgs" : ["/2.png", "/2.png", "/2.png"], "desc" : "Jilbab Pashmina", "Kategori" : "Palestina"},
    {"id" : "10" , "title" : "Pashmina Jersey", "price" : "30K", "imgs" : ["/2.png", "/2.png", "/2.png"], "desc" : "Jilbab Pashmina", "Kategori" : "Palestina"}
]